AUTHORS.rst
CONTRIBUTING.rst
HISTORY.rst
LICENSE
MANIFEST.in
README.rst
setup.cfg
setup.py
docs/Makefile
docs/authors.rst
docs/conf.py
docs/contributing.rst
docs/history.rst
docs/index.rst
docs/installation.rst
docs/make.bat
docs/readme.rst
docs/usage.rst
tests/__init__.py
tests/test_uapycon.py
uapycon/__init__.py
uapycon/uapycon.py
uapycon.egg-info/PKG-INFO
uapycon.egg-info/SOURCES.txt
uapycon.egg-info/dependency_links.txt
uapycon.egg-info/not-zip-safe
uapycon.egg-info/top_level.txt