Metadata-Version: 1.1
Name: uapycon
Version: 0.1.0
Summary: Python package to work with UAPycon site API
Home-page: https://github.com/hotsyk/uapycon
Author: Volodymyr Hotsyk
Author-email: gotsyk@gmail.com
License: BSD
Keywords: uapycon
Platform: UNKNOWN
Classifier: Development Status :: 2 - Pre-Alpha
Classifier: Intended Audience :: Developers
Classifier: License :: OSI Approved :: BSD License
Classifier: Natural Language :: English
Classifier: Programming Language :: Python :: 2
Classifier: Programming Language :: Python :: 2.6
Classifier: Programming Language :: Python :: 2.7
Classifier: Programming Language :: Python :: 3
Classifier: Programming Language :: Python :: 3.3
Classifier: Programming Language :: Python :: 3.4
